[
  {
    "name": "Working",
    "startTime": "10:34",
    "endTime": "10:36",
    "class": "10",
    "type": "excel",
    "file": "Working.xlsx",
    "_id": "6818466b66f26d4875506624"
  },
  {
    "name": "All is well",
    "startTime": "10:48",
    "endTime": "10:49",
    "class": "10",
    "type": "excel",
    "file": "All is well.xlsx",
    "_id": "681849d91ce2cf166500a8a8"
  },
  {
    "name": "king",
    "startTime": "12:53",
    "endTime": "14:00",
    "class": "10",
    "type": "excel",
    "file": "king.xlsx",
    "_id": "6818670b37bea87f0804d381"
  },
  {
    "name": "Integration",
    "startTime": "10:00",
    "endTime": "11:00",
    "class": "10",
    "type": "excel",
    "file": "Integration.xlsx",
    "_id": "681990f2b7b490ddb5f94624"
  },
  {
    "name": "question",
    "startTime": "12:00",
    "endTime": "13:00",
    "class": "10",
    "type": "excel",
    "file": "question.xlsx",
    "_id": "6819adcbb72657019ac834ec"
  },
  {
    "name": "jj",
    "startTime": "12:00",
    "endTime": "13:00",
    "class": "10",
    "type": "excel",
    "file": "jj.xlsx",
    "_id": "6819aed34a8501ba39f3fad4"
  },
  {
    "name": "ooo",
    "startTime": "12:55",
    "endTime": "13:30",
    "class": "10",
    "type": "excel",
    "file": "ooo.xlsx",
    "_id": "6819b98538eb5baf4a3cad11"
  },
  {
    "name": "quizzz",
    "startTime": "15:30",
    "endTime": "17:00",
    "class": "10",
    "type": "excel",
    "file": "quizzz.xlsx",
    "_id": "6819ddb753c48e12e52cedfa"
  },
  {
    "name": "lllal",
    "startTime": "16:40",
    "endTime": "18:00",
    "class": "10",
    "type": "excel",
    "file": "lllal.xlsx",
    "_id": "6819ef2497cfc354b3a244bd"
  },
  {
    "name": "updated",
    "startTime": "11:00",
    "endTime": "13:00",
    "class": "10",
    "type": "excel",
    "file": "updated.xlsx",
    "_id": "681af475c8b9d7e52513d2cb"
  },
  {
    "name": "java",
    "startTime": "12:00",
    "endTime": "13:00",
    "class": "10",
    "type": "excel",
    "file": "java.xlsx",
    "_id": "681b00fbcab55dec1b0746cf"
  },
  {
    "name": "java2",
    "startTime": "13:00",
    "endTime": "13:30",
    "class": "10",
    "type": "excel",
    "file": "java2.xlsx",
    "_id": "681b0ce94b31f773ee948dd2"
  },
  {
    "name": "vvv",
    "startTime": "14:40",
    "endTime": "16:00",
    "class": "10",
    "type": "excel",
    "file": "vvv.xlsx",
    "_id": "681b23d036c94094433a0cb1"
  },
  {
    "name": "ooo",
    "startTime": "16:00",
    "endTime": "17:00",
    "class": "9",
    "type": "excel",
    "file": "ooo.xlsx",
    "_id": "681b36c92744fafac596f814"
  },
  {
    "name": "oo",
    "startTime": "16:00",
    "endTime": "17:00",
    "class": "10",
    "type": "excel",
    "file": "oo.xlsx",
    "_id": "681b37172744fafac596f815"
  },
  {
    "name": "jju",
    "startTime": "16:38",
    "endTime": "19:00",
    "class": "10",
    "type": "excel",
    "file": "jju.xlsx",
    "_id": "681b3f418b0a45deb96ffeb9"
  },
  {
    "name": "all OK",
    "startTime": "10:15",
    "endTime": "12:00",
    "class": "10",
    "type": "excel",
    "file": "all OK.xlsx",
    "_id": "681c380a823e684ed6d10bf7"
  },
  {
    "name": "nenu",
    "startTime": "11:00",
    "endTime": "12:00",
    "class": "10",
    "type": "excel",
    "file": "nenu.xlsx",
    "_id": "681c430d8e0895e7fe54b38b"
  },
  {
    "name": "rrr",
    "startTime": "19:40",
    "endTime": "21:00",
    "class": "8",
    "type": "excel",
    "file": "rrr.xlsx",
    "_id": "6824a5f29885fe26603ef0e2"
  },
  {
    "name": "king ra",
    "startTime": "19:50",
    "endTime": "21:00",
    "class": "8",
    "type": "excel",
    "file": "king ra.xlsx",
    "_id": "6824a8cf5ad2e6264112ea37"
  },
  {
    "name": "king ra retake",
    "startTime": "19:50",
    "endTime": "21:00",
    "class": "999",
    "type": "excel",
    "isStudentSpecific": true,
    "file": "king ra.xlsx"
  },
  {
    "name": "sorry",
    "startTime": "20:00",
    "endTime": "21:00",
    "class": "999",
    "type": "excel",
    "file": "sorry.xlsx",
    "isStudentSpecific": true
  }
]